example_pkg/__about__.py
example_pkg/__init__.py
example_pkg/helpers.py
example_pkg/sub_pkg_1/__init__.py
example_pkg/sub_pkg_1/mod_one.py
example_pkg/sub_pkg_1/mod_two.py
example_pkg/sub_pkg_1/nested_pkg_1/__init__.py
example_pkg/sub_pkg_1/nested_pkg_1/nst_1.py
example_pkg/sub_pkg_2/__init__.py
example_pkg/sub_pkg_2/mod_1.py
example_pkg/sub_pkg_2/mod_2.py
firstNestedPackage_edo-0.0.0.dist-info/LICENSE
firstNestedPackage_edo-0.0.0.dist-info/METADATA
firstNestedPackage_edo-0.0.0.dist-info/WHEEL
firstNestedPackage_edo-0.0.0.dist-info/top_level.txt
firstNestedPackage_edo-0.0.0.dist-info/RECORD
