Metadata-Version: 2.1
Name: firstNestedPackage-edo
Version: 0.0.0
Summary: A example of a nested package
Home-page: UNKNOWN
Author: EdoardoTechie
Author-email: edgr19ab@student.cbs.dk
License: UNKNOWN
Platform: UNKNOWN
Classifier: Programming Language :: Python :: 3
Classifier: License :: OSI Approved :: MIT License
Classifier: Operating System :: OS Independent
Classifier: Development Status :: 1 - Planning
Requires-Python: >=3.6
